<?xml version="1.0" encoding="UTF-8" ?>
<!DOCTYPE mapper PUBLIC "-//mybatis.org//DTD Mapper 3.0//EN" "http://mybatis.org/dtd/mybatis-3-mapper.dtd" >
<mapper namespace="com.myfun.repository.admindb.dao.AdminFafaTaskMapper" >
  <resultMap id="BaseResultMap" type="com.myfun.repository.admindb.po.AdminFafaTask" >
    <!--@mbggenerated-->
    <result column="FAFA_TASK_ID" property="fafaTaskId" jdbcType="INTEGER" />
    <result column="USER_ID" property="userId" jdbcType="INTEGER" />
    <result column="USER_MOBILE" property="userMobile" jdbcType="VARCHAR" />
    <result column="COMP_NO" property="compNo" jdbcType="VARCHAR" />
    <result column="CITY_ID" property="cityId" jdbcType="INTEGER" />
    <result column="CREATION_TIME" property="creationTime" jdbcType="TIMESTAMP" />
    <result column="UPDATE_TIME" property="updateTime" jdbcType="TIMESTAMP" />
    <result column="EXECUTE_STATUS" property="executeStatus" jdbcType="INTEGER" />
    <result column="EXECUTE_MOBILE" property="executeMobile" jdbcType="VARCHAR" />
    <result column="EXECUTE_COUNT" property="executeCount" jdbcType="INTEGER" />
    <result column="TASK_ID" property="taskId" jdbcType="VARCHAR" />
    <result column="TASK_DATA" property="taskData" jdbcType="VARCHAR" />
    <result column="LIMIT_CITY_ID" property="limitCityId" jdbcType="INTEGER" />
    <result column="LIMIT_USER_MOBILE" property="limitUserMobile" jdbcType="VARCHAR" />
  </resultMap>
  <insert id="insert" parameterType="com.myfun.repository.admindb.po.AdminFafaTask" >
    <!--@mbggenerated-->
    <selectKey resultType="java.lang.Integer" keyProperty="fafaTaskId" order="AFTER" >
      SELECT SCOPE_IDENTITY()
    </selectKey>
    insert into FAFA_TASK (USER_ID, USER_MOBILE, COMP_NO, 
      CITY_ID, CREATION_TIME, UPDATE_TIME, 
      EXECUTE_STATUS, EXECUTE_MOBILE, EXECUTE_COUNT, 
      TASK_ID, TASK_DATA, LIMIT_CITY_ID, 
      LIMIT_USER_MOBILE)
    values (#{userId,jdbcType=INTEGER}, #{userMobile,jdbcType=VARCHAR}, #{compNo,jdbcType=VARCHAR}, 
      #{cityId,jdbcType=INTEGER}, #{creationTime,jdbcType=TIMESTAMP}, #{updateTime,jdbcType=TIMESTAMP}, 
      #{executeStatus,jdbcType=INTEGER}, #{executeMobile,jdbcType=VARCHAR}, #{executeCount,jdbcType=INTEGER}, 
      #{taskId,jdbcType=VARCHAR}, #{taskData,jdbcType=VARCHAR}, #{limitCityId,jdbcType=INTEGER}, 
      #{limitUserMobile,jdbcType=VARCHAR})
  </insert>
  <insert id="insertSelective" parameterType="com.myfun.repository.admindb.po.AdminFafaTask" >
    <!--@mbggenerated-->
    <selectKey resultType="java.lang.Integer" keyProperty="fafaTaskId" order="AFTER" >
      SELECT SCOPE_IDENTITY()
    </selectKey>
    insert into FAFA_TASK
    <trim prefix="(" suffix=")" suffixOverrides="," >
      <if test="userId != null" >
        USER_ID,
      </if>
      <if test="userMobile != null" >
        USER_MOBILE,
      </if>
      <if test="compNo != null" >
        COMP_NO,
      </if>
      <if test="cityId != null" >
        CITY_ID,
      </if>
      <if test="creationTime != null" >
        CREATION_TIME,
      </if>
      <if test="updateTime != null" >
        UPDATE_TIME,
      </if>
      <if test="executeStatus != null" >
        EXECUTE_STATUS,
      </if>
      <if test="executeMobile != null" >
        EXECUTE_MOBILE,
      </if>
      <if test="executeCount != null" >
        EXECUTE_COUNT,
      </if>
      <if test="taskId != null" >
        TASK_ID,
      </if>
      <if test="taskData != null" >
        TASK_DATA,
      </if>
      <if test="limitCityId != null" >
        LIMIT_CITY_ID,
      </if>
      <if test="limitUserMobile != null" >
        LIMIT_USER_MOBILE,
      </if>
    </trim>
    <trim prefix="values (" suffix=")" suffixOverrides="," >
      <if test="userId != null" >
        #{userId,jdbcType=INTEGER},
      </if>
      <if test="userMobile != null" >
        #{userMobile,jdbcType=VARCHAR},
      </if>
      <if test="compNo != null" >
        #{compNo,jdbcType=VARCHAR},
      </if>
      <if test="cityId != null" >
        #{cityId,jdbcType=INTEGER},
      </if>
      <if test="creationTime != null" >
        #{creationTime,jdbcType=TIMESTAMP},
      </if>
      <if test="updateTime != null" >
        #{updateTime,jdbcType=TIMESTAMP},
      </if>
      <if test="executeStatus != null" >
        #{executeStatus,jdbcType=INTEGER},
      </if>
      <if test="executeMobile != null" >
        #{executeMobile,jdbcType=VARCHAR},
      </if>
      <if test="executeCount != null" >
        #{executeCount,jdbcType=INTEGER},
      </if>
      <if test="taskId != null" >
        #{taskId,jdbcType=VARCHAR},
      </if>
      <if test="taskData != null" >
        #{taskData,jdbcType=VARCHAR},
      </if>
      <if test="limitCityId != null" >
        #{limitCityId,jdbcType=INTEGER},
      </if>
      <if test="limitUserMobile != null" >
        #{limitUserMobile,jdbcType=VARCHAR},
      </if>
    </trim>
  </insert>
</mapper>